{
	"info": {
		"_postman_id": "b00cdbff-5e77-4cf0-864e-75686b02ebb7",
		"name": "AndGarivara Listing",
		"schema": "https://schema.getpostman.com/json/collection/v2.1.0/collection.json"
	},
	"item": [
		{
			"name": "Admin",
			"item": [
				{
					"name": "Vehicle Types",
					"item": [
						{
							"name": "Edit Vehicle Type",
							"request": {
								"method": "POST",
								"header": [],
								"body": {
									"mode": "raw",
									"raw": "{\r\n    \"_id\":\"5f65d65760b9f0120064af2a\",\r\n    \"title\":\"Micro Bus\"\r\n}",
									"options": {
										"raw": {
											"language": "json"
										}
									}
								},
								"url": {
									"raw": "http://localhost:5000/admin/edit_vehicle_type",
									"protocol": "http",
									"host": [
										"localhost"
									],
									"port": "5000",
									"path": [
										"admin",
										"edit_vehicle_type"
									]
								}
							},
							"response": []
						},
						{
							"name": "Add Vehicle Type",
							"request": {
								"method": "POST",
								"header": [],
								"body": {
									"mode": "raw",
									"raw": "{\r\n   \"title\": \"Ambulance\"\r\n}",
									"options": {
										"raw": {
											"language": "json"
										}
									}
								},
								"url": {
									"raw": "http://localhost:5000/admin/add_vehicle_type",
									"protocol": "http",
									"host": [
										"localhost"
									],
									"port": "5000",
									"path": [
										"admin",
										"add_vehicle_type"
									]
								}
							},
							"response": []
						},
						{
							"name": "Delete Vehicle Type",
							"request": {
								"method": "POST",
								"header": [],
								"body": {
									"mode": "raw",
									"raw": " {\r\n            \"_id\": \"5f68377ba0e16454400b17b0\"\r\n        }",
									"options": {
										"raw": {
											"language": "json"
										}
									}
								},
								"url": {
									"raw": "http://localhost:5000/admin/delete_vehicle_type",
									"protocol": "http",
									"host": [
										"localhost"
									],
									"port": "5000",
									"path": [
										"admin",
										"delete_vehicle_type"
									]
								}
							},
							"response": []
						},
						{
							"name": "Vehicle Type List",
							"request": {
								"method": "POST",
								"header": [],
								"body": {
									"mode": "raw",
									"raw": "",
									"options": {
										"raw": {
											"language": "json"
										}
									}
								},
								"url": {
									"raw": "http://localhost:5000/admin/vehicle_type_list",
									"protocol": "http",
									"host": [
										"localhost"
									],
									"port": "5000",
									"path": [
										"admin",
										"vehicle_type_list"
									]
								}
							},
							"response": []
						}
					],
					"protocolProfileBehavior": {},
					"_postman_isSubFolder": true
				},
				{
					"name": "Vehicles",
					"item": [
						{
							"name": "Add Vehicle",
							"request": {
								"method": "POST",
								"header": [],
								"body": {
									"mode": "raw",
									"raw": "{\r\n        \"user_id\":\"5f67189a034c350d7bd2e43c\",\r\n        \"title\": \"Micro Bus\",\r\n        \"vehicle_type\": \"5f65d65760b9f0120064af2a\",\r\n        \"description\": \"Micro Bus Rent\",\r\n        \"country\": \"bd\",\r\n        \"city\": \"Khulna\",\r\n        \"car_location\": \"Gollamari\",\r\n        \"total_seat\": 13,\r\n        \"min_price_per_day\": 8000,\r\n        \"cover_img\": \"\",\r\n        \"brand\": \"Corolla\",\r\n        \"model\": \"SUV\",\r\n        \"year_of_manufacture\": \"2016\",\r\n        \"color\": \"black\",\r\n        \"ac\": false,\r\n        \"vehicle_imgs\": [           \r\n        ]\r\n    }",
									"options": {
										"raw": {
											"language": "json"
										}
									}
								},
								"url": {
									"raw": "http://localhost:5000/admin/add_vehicle",
									"protocol": "http",
									"host": [
										"localhost"
									],
									"port": "5000",
									"path": [
										"admin",
										"add_vehicle"
									]
								}
							},
							"response": []
						},
						{
							"name": "Vehicle List",
							"request": {
								"method": "POST",
								"header": [],
								"body": {
									"mode": "raw",
									"raw": "",
									"options": {
										"raw": {
											"language": "json"
										}
									}
								},
								"url": {
									"raw": "http://localhost:5000/admin/vehicle_list",
									"protocol": "http",
									"host": [
										"localhost"
									],
									"port": "5000",
									"path": [
										"admin",
										"vehicle_list"
									]
								}
							},
							"response": []
						},
						{
							"name": "Edit Vehicle",
							"request": {
								"method": "POST",
								"header": [],
								"body": {
									"mode": "raw",
									"raw": "{\r\n        \"_id\": \"5f6842398ae00e3b9541c7c8\",  \r\n        \"user_id\":\"5f6344477e377e0b80d01bbf\",\r\n        \"title\": \"Bike Rent\",\r\n        \"vehicle_type\": \"5f65d65760b9f0120064af29\",\r\n        \"description\": \"Bike\",\r\n        \"country\": \"bd\",\r\n        \"city\": \"Khulna\",\r\n        \"car_location\": \"Nirala\",\r\n        \"total_seat\": 2,\r\n        \"min_price_per_day\": 1500,\r\n        \"cover_img\": \"\",\r\n        \"brand\": \"Yamaha\",\r\n        \"model\": \"Valentino\",\r\n        \"year_of_manufacture\": \"2016\",\r\n        \"color\": \"black-red\",\r\n        \"ac\": false,\r\n        \"vehicle_imgs\": [           \r\n        ]\r\n    }",
									"options": {
										"raw": {
											"language": "json"
										}
									}
								},
								"url": {
									"raw": "http://localhost:5000/admin/edit_vehicle",
									"protocol": "http",
									"host": [
										"localhost"
									],
									"port": "5000",
									"path": [
										"admin",
										"edit_vehicle"
									]
								}
							},
							"response": []
						},
						{
							"name": "Delete Vehicle",
							"request": {
								"method": "POST",
								"header": [],
								"body": {
									"mode": "raw",
									"raw": "{\r\n       \"_id\":\"5f684446ef9b2d92f7e25356\",\r\n        \"del_satus\": false,\r\n        \"del_resone\": \"test Delete\"\r\n}",
									"options": {
										"raw": {
											"language": "json"
										}
									}
								},
								"url": {
									"raw": "http://localhost:5000/admin/delete_vehicle",
									"protocol": "http",
									"host": [
										"localhost"
									],
									"port": "5000",
									"path": [
										"admin",
										"delete_vehicle"
									]
								}
							},
							"response": []
						}
					],
					"protocolProfileBehavior": {},
					"_postman_isSubFolder": true
				},
				{
					"name": "Users",
					"item": [
						{
							"name": "Delete User",
							"request": {
								"method": "POST",
								"header": [],
								"body": {
									"mode": "raw",
									"raw": "\r\n{\r\n    \"_id\":\"5f683cbb7215562e44d863eb\"\r\n}",
									"options": {
										"raw": {
											"language": "json"
										}
									}
								},
								"url": {
									"raw": "http://localhost:5000/admin/delete_user",
									"protocol": "http",
									"host": [
										"localhost"
									],
									"port": "5000",
									"path": [
										"admin",
										"delete_user"
									]
								}
							},
							"response": []
						},
						{
							"name": "User List",
							"request": {
								"method": "POST",
								"header": [],
								"url": {
									"raw": "http://localhost:5000/admin/user_list",
									"protocol": "http",
									"host": [
										"localhost"
									],
									"port": "5000",
									"path": [
										"admin",
										"user_list"
									]
								}
							},
							"response": []
						},
						{
							"name": "Add User",
							"request": {
								"method": "POST",
								"header": [],
								"body": {
									"mode": "raw",
									"raw": "{\r\n        \"f_name\":\"Raju\",\r\n        \"l_name\": \"Da\",        \r\n        \"password\":\"1213\",\r\n        \"phn_no\": \"01856956475\"\r\n}",
									"options": {
										"raw": {
											"language": "json"
										}
									}
								},
								"url": {
									"raw": "http://localhost:5000/admin/add_user",
									"protocol": "http",
									"host": [
										"localhost"
									],
									"port": "5000",
									"path": [
										"admin",
										"add_user"
									]
								}
							},
							"response": []
						}
					],
					"protocolProfileBehavior": {},
					"_postman_isSubFolder": true
				},
				{
					"name": "City",
					"item": [
						{
							"name": "Add City",
							"request": {
								"method": "POST",
								"header": [],
								"body": {
									"mode": "raw",
									"raw": "{\r\n       \"city\": \"barguna\"\r\n\r\n}",
									"options": {
										"raw": {
											"language": "json"
										}
									}
								},
								"url": {
									"raw": "http://localhost:5000/admin/add_city",
									"protocol": "http",
									"host": [
										"localhost"
									],
									"port": "5000",
									"path": [
										"admin",
										"add_city"
									]
								}
							},
							"response": []
						},
						{
							"name": "Edit City",
							"request": {
								"method": "POST",
								"header": [],
								"body": {
									"mode": "raw",
									"raw": "{\r\n       \"city\": \"Barguna\",\r\n        \"_id\":\"5f6870ce8e4335ceef53e130\"\r\n}",
									"options": {
										"raw": {
											"language": "json"
										}
									}
								},
								"url": {
									"raw": "http://localhost:5000/admin/edit_city",
									"protocol": "http",
									"host": [
										"localhost"
									],
									"port": "5000",
									"path": [
										"admin",
										"edit_city"
									]
								}
							},
							"response": []
						},
						{
							"name": "City List",
							"request": {
								"method": "POST",
								"header": [],
								"body": {
									"mode": "raw",
									"raw": "",
									"options": {
										"raw": {
											"language": "json"
										}
									}
								},
								"url": {
									"raw": "http://localhost:5000/admin/city_list",
									"protocol": "http",
									"host": [
										"localhost"
									],
									"port": "5000",
									"path": [
										"admin",
										"city_list"
									]
								}
							},
							"response": []
						},
						{
							"name": "Delete City",
							"request": {
								"method": "POST",
								"header": [],
								"body": {
									"mode": "raw",
									"raw": "{\r\n       \r\n        \"_id\":\"5f6871338e4335ceef53e131\"\r\n}",
									"options": {
										"raw": {
											"language": "json"
										}
									}
								},
								"url": {
									"raw": "http://localhost:5000/admin/delete_city",
									"protocol": "http",
									"host": [
										"localhost"
									],
									"port": "5000",
									"path": [
										"admin",
										"delete_city"
									]
								}
							},
							"response": []
						}
					],
					"protocolProfileBehavior": {},
					"_postman_isSubFolder": true
				},
				{
					"name": "Admin Login",
					"request": {
						"method": "POST",
						"header": [],
						"body": {
							"mode": "raw",
							"raw": "{\r\n    \"phn_no\":\"admin\",\r\n    \"password\":\"admin\"\r\n}",
							"options": {
								"raw": {
									"language": "json"
								}
							}
						},
						"url": {
							"raw": "http://localhost:5000/admin/login",
							"protocol": "http",
							"host": [
								"localhost"
							],
							"port": "5000",
							"path": [
								"admin",
								"login"
							]
						}
					},
					"response": []
				}
			],
			"protocolProfileBehavior": {}
		},
		{
			"name": "User",
			"item": [
				{
					"name": "Vehicle",
					"item": [
						{
							"name": "Add Vehicle",
							"request": {
								"method": "POST",
								"header": [],
								"body": {
									"mode": "raw",
									"raw": "{\r\n        \"user_id\":\"5f6344477e377e0b80d01bbf\",\r\n        \"title\": \"Bike Rent\",\r\n        \"vehicle_type\": \"5f65d65760b9f0120064af29\",\r\n        \"description\": \"Bike\",\r\n        \"country\": \"bd\",\r\n        \"city\": \"Khulna\",\r\n        \"car_location\": \"Nirala\",\r\n        \"total_seat\": 2,\r\n        \"min_price_per_day\": 500,\r\n        \"cover_img\": \"\",\r\n        \"brand\": \"Yamaha\",\r\n        \"model\": \"Valentino\",\r\n        \"year_of_manufacture\": \"2016\",\r\n        \"color\": \"black\",\r\n        \"ac\": false,\r\n        \"vehicle_imgs\": [           \r\n        ]\r\n    }",
									"options": {
										"raw": {
											"language": "json"
										}
									}
								},
								"url": {
									"raw": "http://localhost:5000/admin/add_vehicle",
									"protocol": "http",
									"host": [
										"localhost"
									],
									"port": "5000",
									"path": [
										"admin",
										"add_vehicle"
									]
								}
							},
							"response": []
						},
						{
							"name": "Delete Vehicle",
							"request": {
								"method": "POST",
								"header": [],
								"body": {
									"mode": "raw",
									"raw": "{\r\n       \"_id\":\"5f65da3defe823779f0722ef\",\r\n        \"del_satus\": false,\r\n        \"del_resone\": \"test Delete\",\r\n        \"del_date\":\"\"\r\n}",
									"options": {
										"raw": {
											"language": "json"
										}
									}
								},
								"url": {
									"raw": "http://localhost:5000/user/delete_vehicle",
									"protocol": "http",
									"host": [
										"localhost"
									],
									"port": "5000",
									"path": [
										"user",
										"delete_vehicle"
									]
								}
							},
							"response": []
						},
						{
							"name": "Vehicle List",
							"request": {
								"method": "POST",
								"header": [],
								"body": {
									"mode": "raw",
									"raw": "{\r\n        \"user_id\":\"5f6344477e377e0b80d01bbf\"\r\n}",
									"options": {
										"raw": {
											"language": "json"
										}
									}
								},
								"url": {
									"raw": "http://localhost:5000/user/vehicle_list",
									"protocol": "http",
									"host": [
										"localhost"
									],
									"port": "5000",
									"path": [
										"user",
										"vehicle_list"
									]
								}
							},
							"response": []
						},
						{
							"name": "Edit Vehicle",
							"request": {
								"method": "POST",
								"header": [],
								"body": {
									"mode": "raw",
									"raw": "{\r\n       \"_id\":\"5f65da3defe823779f0722ef\",\r\n        \"user_id\":\"5f6344477e377e0b80d01bbf\",\r\n        \"title\": \"Car Rent\",\r\n        \"vehicle_type\": \"5f65d65760b9f0120064af28\",\r\n        \"description\": \"car descriptions\",\r\n        \"country\": \"bd\",\r\n        \"city\": \"khulna\",\r\n        \"car_location\": \"Gollamari\",\r\n        \"total_seat\": 4,\r\n        \"min_price_per_day\": 3000,\r\n        \"cover_img\": \"\",\r\n        \"brand\": \"Toyota\",\r\n        \"model\": \"X-fielder\",\r\n        \"year_of_manufacture\": \"2014\",\r\n        \"color\": \"Red\",\r\n        \"ac\": true,\r\n        \"vehicle_imgs\": [           \r\n        ]\r\n    }",
									"options": {
										"raw": {
											"language": "json"
										}
									}
								},
								"url": {
									"raw": "http://localhost:5000/user/edit_vehicle",
									"protocol": "http",
									"host": [
										"localhost"
									],
									"port": "5000",
									"path": [
										"user",
										"edit_vehicle"
									]
								}
							},
							"response": []
						}
					],
					"protocolProfileBehavior": {},
					"_postman_isSubFolder": true
				},
				{
					"name": "Profile",
					"item": [
						{
							"name": "Delete Profile",
							"request": {
								"method": "POST",
								"header": [],
								"body": {
									"mode": "raw",
									"raw": "{\r\n    \"_id\":\"5f65976b777625ee625fe2fc\",\r\n    \"del_satus\": \"\",\r\n    \"del_resone\": \"deleted profile\"\r\n}",
									"options": {
										"raw": {
											"language": "json"
										}
									}
								},
								"url": {
									"raw": "http://localhost:5000/user/delete_profile",
									"protocol": "http",
									"host": [
										"localhost"
									],
									"port": "5000",
									"path": [
										"user",
										"delete_profile"
									]
								}
							},
							"response": []
						},
						{
							"name": "Profile Edit",
							"request": {
								"method": "POST",
								"header": [],
								"body": {
									"mode": "raw",
									"raw": "{\r\n    \"_id\":\"5f6344477e377e0b80d01bbf\",\r\n    \"f_name\": \"Tama\",\r\n    \"l_name\": \"Sarker\",\r\n    \"email\": \"tsarker@gmail\",\r\n    \"country\": \"Bangladesh\",\r\n    \"city\": \"Barishal\",\r\n    \"address\": \"Khulna\",\r\n    \"password\": \"1111\",\r\n    \"phn_no\":\"01717302554\"\r\n}",
									"options": {
										"raw": {
											"language": "json"
										}
									}
								},
								"url": {
									"raw": "http://localhost:5000/user/profile_edit",
									"protocol": "http",
									"host": [
										"localhost"
									],
									"port": "5000",
									"path": [
										"user",
										"profile_edit"
									]
								}
							},
							"response": []
						}
					],
					"protocolProfileBehavior": {},
					"_postman_isSubFolder": true
				},
				{
					"name": "Favorites",
					"item": [
						{
							"name": "Favorites List",
							"request": {
								"method": "POST",
								"header": [],
								"body": {
									"mode": "raw",
									"raw": "{\r\n        \"_id\":\"5f671aa9563ce0014a00be7a\"\r\n}",
									"options": {
										"raw": {
											"language": "json"
										}
									}
								},
								"url": {
									"raw": "http://localhost:5000/user/favorite_list",
									"protocol": "http",
									"host": [
										"localhost"
									],
									"port": "5000",
									"path": [
										"user",
										"favorite_list"
									]
								}
							},
							"response": []
						},
						{
							"name": "Add Favorites",
							"request": {
								"method": "POST",
								"header": [],
								"body": {
									"mode": "raw",
									"raw": "{\r\n    \"car_id\":\"5f671ddbb24346fa12f94d59\",\r\n    \"_id\":\"5f671aa9563ce0014a00be7a\"\r\n}",
									"options": {
										"raw": {
											"language": "json"
										}
									}
								},
								"url": {
									"raw": "http://localhost:5000/user/delete_favorites",
									"protocol": "http",
									"host": [
										"localhost"
									],
									"port": "5000",
									"path": [
										"user",
										"delete_favorites"
									]
								}
							},
							"response": []
						},
						{
							"name": "Delete Favorites",
							"request": {
								"method": "POST",
								"header": [],
								"body": {
									"mode": "raw",
									"raw": "{\r\n    \"car_id\":\"5f671ddbb24346fa12f94d59\",\r\n    \"_id\":\"5f671aa9563ce0014a00be7a\"\r\n}",
									"options": {
										"raw": {
											"language": "json"
										}
									}
								},
								"url": {
									"raw": "http://localhost:5000/user/delete_favorites",
									"protocol": "http",
									"host": [
										"localhost"
									],
									"port": "5000",
									"path": [
										"user",
										"delete_favorites"
									]
								}
							},
							"response": []
						}
					],
					"protocolProfileBehavior": {},
					"_postman_isSubFolder": true
				},
				{
					"name": "User Login",
					"request": {
						"method": "POST",
						"header": [],
						"body": {
							"mode": "raw",
							"raw": "{\r\n    \"phn_no\": \"01717302554\",\r\n    \"password\": \"1111\"\r\n}",
							"options": {
								"raw": {
									"language": "json"
								}
							}
						},
						"url": {
							"raw": "http://localhost:5000/user/login",
							"protocol": "http",
							"host": [
								"localhost"
							],
							"port": "5000",
							"path": [
								"user",
								"login"
							]
						}
					},
					"response": []
				},
				{
					"name": "User Signup",
					"request": {
						"method": "POST",
						"header": [],
						"body": {
							"mode": "raw",
							"raw": "{\r\n        \"f_name\":\"Raju\",\r\n        \"l_name\": \"Da\",        \r\n        \"password\":\"1213\",\r\n        \"phn_no\": \"01856956475\"\r\n}",
							"options": {
								"raw": {
									"language": "json"
								}
							}
						},
						"url": {
							"raw": "http://localhost:5000/user/signup",
							"protocol": "http",
							"host": [
								"localhost"
							],
							"port": "5000",
							"path": [
								"user",
								"signup"
							]
						}
					},
					"response": []
				}
			],
			"protocolProfileBehavior": {}
		},
		{
			"name": "FrontEnd",
			"item": [
				{
					"name": "Vehicle Profile",
					"request": {
						"method": "POST",
						"header": [],
						"body": {
							"mode": "raw",
							"raw": "{\r\n       \"_id\":\"5f65dab5efe823779f0722f0\"\r\n}",
							"options": {
								"raw": {
									"language": "json"
								}
							}
						},
						"url": {
							"raw": "http://localhost:5000/and_gari_vara/vehicle_profile",
							"protocol": "http",
							"host": [
								"localhost"
							],
							"port": "5000",
							"path": [
								"and_gari_vara",
								"vehicle_profile"
							]
						}
					},
					"response": []
				},
				{
					"name": "Listing Homepage",
					"request": {
						"method": "POST",
						"header": [],
						"body": {
							"mode": "raw",
							"raw": "",
							"options": {
								"raw": {
									"language": "json"
								}
							}
						},
						"url": {
							"raw": "http://localhost:5000//and_gari_vara/list_homepage",
							"protocol": "http",
							"host": [
								"localhost"
							],
							"port": "5000",
							"path": [
								"",
								"and_gari_vara",
								"list_homepage"
							]
						}
					},
					"response": []
				},
				{
					"name": "Search Result Page",
					"request": {
						"method": "POST",
						"header": [],
						"body": {
							"mode": "raw",
							"raw": "{\r\n    \"vehicle_type\":\"\",\r\n    \"city\": \"\"\r\n}",
							"options": {
								"raw": {
									"language": "json"
								}
							}
						},
						"url": {
							"raw": "http://localhost:5000//and_gari_vara/search_result_page",
							"protocol": "http",
							"host": [
								"localhost"
							],
							"port": "5000",
							"path": [
								"",
								"and_gari_vara",
								"search_result_page"
							]
						}
					},
					"response": []
				}
			],
			"protocolProfileBehavior": {}
		}
	],
	"protocolProfileBehavior": {}
}